aiohttp_oauthlib.py
aiohttp_oauthlib-0.1.0.dist-info/LICENCE
aiohttp_oauthlib-0.1.0.dist-info/METADATA
aiohttp_oauthlib-0.1.0.dist-info/WHEEL
aiohttp_oauthlib-0.1.0.dist-info/top_level.txt
aiohttp_oauthlib-0.1.0.dist-info/RECORD
